faasmctl/__init__.py
faasmctl/main.py
faasmctl/bin/gen_proto_files.py
faasmctl/tasks/__init__.py
faasmctl/tasks/cli.py
faasmctl/tasks/delete.py
faasmctl/tasks/deploy.py
faasmctl/tasks/flush.py
faasmctl/tasks/generate.py
faasmctl/tasks/invoke.py
faasmctl/tasks/logs.py
faasmctl/tasks/monitor.py
faasmctl/tasks/restart.py
faasmctl/tasks/scale.py
faasmctl/tasks/status.py
faasmctl/tasks/stream.py
faasmctl/tasks/upload.py
faasmctl/util/backend.py
faasmctl/util/batch.py
faasmctl/util/compose.py
faasmctl/util/config.py
faasmctl/util/deploy.py
faasmctl/util/docker.py
faasmctl/util/env.py
faasmctl/util/faasm.py
faasmctl/util/flush.py
faasmctl/util/invoke.py
faasmctl/util/k8s.py
faasmctl/util/message.py
faasmctl/util/network.py
faasmctl/util/planner.py
faasmctl/util/random.py
faasmctl/util/restart.py
faasmctl/util/results.py
faasmctl/util/time.py
faasmctl/util/upload.py
faasmctl/util/version.py
faasmctl/util/gen_proto/faabric_pb2.py
faasmctl/util/gen_proto/planner_pb2.py
myfaasmctl-0.1.18.dist-info/licenses/LICENSE.md
myfaasmctl-0.1.18.dist-info/METADATA
myfaasmctl-0.1.18.dist-info/WHEEL
myfaasmctl-0.1.18.dist-info/entry_points.txt
myfaasmctl-0.1.18.dist-info/top_level.txt
myfaasmctl-0.1.18.dist-info/RECORD
